monkeycall/__init__.py
monkeycall/helper.py
monkeycall/howler_monkey.py
monkeycall/spider_monkey.py
monkeycall/custom_objects/__init__.py
monkeycall/custom_objects/conv_blocks.py
monkeycall/custom_objects/custom_keras_layers.py
monkeycall/custom_objects/local_pooling.py
monkeycall/custom_objects/spider_monkey_custom_objects.py
monkeycall/upload/__init__.py
monkeycall/upload/from_tf1/__init__.py
monkeycall/upload/from_tf1/convert_model.py
monkeycall/upload/from_tf1/upload_model.py
monkeycall/upload/from_tf2/__init__.py
monkeycall/upload/from_tf2/test.py
monkeycall/upload/from_tf2/upload.py
monkeycall-0.0.3.dev0.dist-info/licenses/LICENSE
monkeycall-0.0.3.dev0.dist-info/METADATA
monkeycall-0.0.3.dev0.dist-info/WHEEL
monkeycall-0.0.3.dev0.dist-info/top_level.txt
monkeycall-0.0.3.dev0.dist-info/RECORD
