Metadata-Version: 2.4
Name: monkeycall
Version: 0.0.3.dev0
Summary: Detect (spider/howler) monkey calls using pretrained TF2 models from Hugging Face.
Author-email: Georgios Rizos <georgevrizos@gmail.com>
License: MIT
Project-URL: Homepage, https://huggingface.co/georgiosrizos/spider-monkey-detector-SEResNet
Project-URL: Source, https://github.com/georgiosrizos/monkeycall
Requires-Python: >=3.10
License-File: LICENSE
Requires-Dist: tensorflow==2.20.0
Requires-Dist: huggingface_hub==0.34.4
Requires-Dist: librosa==0.11.0
Requires-Dist: pandas==2.3.2
Dynamic: license-file
